odoo/addons/ebill_paynet_customer_free_ref/README.rst
odoo/addons/ebill_paynet_customer_free_ref/__init__.py
odoo/addons/ebill_paynet_customer_free_ref/__manifest__.py
odoo/addons/ebill_paynet_customer_free_ref/i18n/ebill_paynet_customer_free_ref.pot
odoo/addons/ebill_paynet_customer_free_ref/models/__init__.py
odoo/addons/ebill_paynet_customer_free_ref/models/account_move.py
odoo/addons/ebill_paynet_customer_free_ref/models/sale_order.py
odoo/addons/ebill_paynet_customer_free_ref/readme/CONTRIBUTORS.rst
odoo/addons/ebill_paynet_customer_free_ref/readme/DESCRIPTION.rst
odoo/addons/ebill_paynet_customer_free_ref/static/description/icon.png
odoo/addons/ebill_paynet_customer_free_ref/static/description/index.html
odoo/addons/ebill_paynet_customer_free_ref/tests/__init__.py
odoo/addons/ebill_paynet_customer_free_ref/tests/test_ebill_paynet_customer_free_ref.py
odoo/addons/ebill_paynet_customer_free_ref/tests/examples/invoice_b2b.xml
odoo13_addon_ebill_paynet_customer_free_ref-13.0.1.0.1.dist-info/METADATA
odoo13_addon_ebill_paynet_customer_free_ref-13.0.1.0.1.dist-info/WHEEL
odoo13_addon_ebill_paynet_customer_free_ref-13.0.1.0.1.dist-info/top_level.txt
odoo13_addon_ebill_paynet_customer_free_ref-13.0.1.0.1.dist-info/RECORD
